MiejskiDefinicja.py
Sprawdzacz.py
Tester.py
__init__.py
miejskiapi-1.0.0.dist-info/METADATA
miejskiapi-1.0.0.dist-info/WHEEL
miejskiapi-1.0.0.dist-info/top_level.txt
miejskiapi-1.0.0.dist-info/RECORD
